vedro/__init__.py
vedro/__main__.py
vedro/_catched.py
vedro/_config.py
vedro/_context.py
vedro/_effect.py
vedro/_interface.py
vedro/_main.py
vedro/_params.py
vedro/_scenario.py
vedro/_tags.py
vedro/_version.py
vedro/py.typed
vedro/_test_utils/__init__.py
vedro/commands/__init__.py
vedro/commands/_cmd_arg_parser.py
vedro/commands/_command.py
vedro/commands/plugin_command/__init__.py
vedro/commands/plugin_command/_fetch_plugins.py
vedro/commands/plugin_command/_get_plugin_info.py
vedro/commands/plugin_command/_install_plugin.py
vedro/commands/plugin_command/_plugin_command.py
vedro/commands/plugin_command/plugin_manager/__init__.py
vedro/commands/plugin_command/plugin_manager/_config_generator.py
vedro/commands/plugin_command/plugin_manager/_config_markup.py
vedro/commands/plugin_command/plugin_manager/_config_parser.py
vedro/commands/plugin_command/plugin_manager/_config_updater.py
vedro/commands/plugin_command/plugin_manager/_plugin_manager.py
vedro/commands/run_command/__init__.py
vedro/commands/run_command/_config_validator.py
vedro/commands/run_command/_plugin_config_validator.py
vedro/commands/run_command/_plugin_registrar.py
vedro/commands/run_command/_run_command.py
vedro/commands/version_command/__init__.py
vedro/commands/version_command/_version_command.py
vedro/config/__init__.py
vedro/core/__init__.py
vedro/core/_artifacts.py
vedro/core/_container.py
vedro/core/_dispatcher.py
vedro/core/_event.py
vedro/core/_exc_info.py
vedro/core/_meta_data.py
vedro/core/_plugin.py
vedro/core/_report.py
vedro/core/_scenario_meta.py
vedro/core/_step_result.py
vedro/core/_virtual_scenario.py
vedro/core/_virtual_step.py
vedro/core/_config_loader/__init__.py
vedro/core/_module_loader/__init__.py
vedro/core/_scenario_discoverer/__init__.py
vedro/core/_scenario_finder/__init__.py
vedro/core/_scenario_finder/_file_filters/__init__.py
vedro/core/_scenario_loader/__init__.py
vedro/core/_scenario_orderer/__init__.py
vedro/core/_scenario_result/__init__.py
vedro-1.15.1.dist-info/licenses/LICENSE
vedro-1.15.1.dist-info/METADATA
vedro-1.15.1.dist-info/WHEEL
vedro-1.15.1.dist-info/entry_points.txt
vedro-1.15.1.dist-info/top_level.txt
vedro-1.15.1.dist-info/RECORD
