Metadata-Version: 2.4
Name: vedro
Version: 1.15.1
Summary: Pragmatic Testing Framework
Home-page: https://github.com/vedro-universe/vedro
Author: Nikita Tsvetkov
Author-email: tsv1@fastmail.com
License: Apache-2.0
Project-URL: Docs, https://vedro.io/
Project-URL: GitHub, https://github.com/vedro-universe/vedro
Classifier: Intended Audience :: Developers
Classifier: License :: OSI Approved :: Apache Software License
Classifier: Programming Language :: Python :: 3.9
Classifier: Programming Language :: Python :: 3.10
Classifier: Programming Language :: Python :: 3.11
Classifier: Programming Language :: Python :: 3.12
Classifier: Programming Language :: Python :: 3.13
Classifier: Topic :: Software Development
Classifier: Typing :: Typed
Requires-Python: >=3.8
License-File: LICENSE
Requires-Dist: cabina<2.0,>=0.7
Requires-Dist: filelock<4.0,>=3.5
Requires-Dist: niltype<2.0,>=0.3
Requires-Dist: pyparsing<4.0,>=3.0
Requires-Dist: rich<14.0,>=11.0
Dynamic: author
Dynamic: author-email
Dynamic: classifier
Dynamic: description
Dynamic: description-content-type
Dynamic: home-page
Dynamic: license
Dynamic: license-file
Dynamic: project-url
Dynamic: requires-dist
Dynamic: requires-python
Dynamic: summary
